dmdslab/__init__.py
dmdslab/datasets/__init__.py
dmdslab/datasets/ml_data_container.py
dmdslab/datasets/uci/__init__.py
dmdslab/datasets/uci/uci_cache.py
dmdslab/datasets/uci/uci_exceptions.py
dmdslab/datasets/uci/uci_manager.py
dmdslab/datasets/uci/uci_metadata.py
dmdslab/datasets/uci/uci_types.py
dmdslab/datasets/uci/uci_utils.py
dmdslab-2.0.0.dist-info/licenses/LICENSE
dmdslab-2.0.0.dist-info/METADATA
dmdslab-2.0.0.dist-info/WHEEL
dmdslab-2.0.0.dist-info/top_level.txt
dmdslab-2.0.0.dist-info/RECORD
