Metadata-Version: 2.4
Name: DmDSLab
Version: 2.0.0
Summary: Data Science Laboratory Toolkit - инструменты для эффективных исследований
Author-email: Dmatryus Detry <dmatryus.sqrt49@yandex.ru>
License: Apache-2.0
Project-URL: Homepage, https://github.com/Dmatryus/DmDSLab
Project-URL: Documentation, https://github.com/Dmatryus/DmDSLab/wiki
Project-URL: Repository, https://github.com/Dmatryus/DmDSLab
Project-URL: Bug Tracker, https://github.com/Dmatryus/DmDSLab/issues
Project-URL: Changelog, https://github.com/Dmatryus/DmDSLab/blob/main/CHANGELOG.md
Keywords: data-science,machine-learning,datasets,uci,data-preprocessing,research-tools
Classifier: Development Status :: 4 - Beta
Classifier: Intended Audience :: Science/Research
Classifier: Intended Audience :: Developers
Classifier: License :: OSI Approved :: Apache Software License
Classifier: Operating System :: OS Independent
Classifier: Programming Language :: Python :: 3
Classifier: Programming Language :: Python :: 3.11
Classifier: Programming Language :: Python :: 3.12
Classifier: Programming Language :: Python :: 3 :: Only
Classifier: Topic :: Scientific/Engineering
Classifier: Topic :: Scientific/Engineering :: Artificial Intelligence
Classifier: Topic :: Software Development :: Libraries :: Python Modules
Requires-Python: >=3.11
License-File: LICENSE
Requires-Dist: pandas>=1.5.0
Requires-Dist: numpy>=1.21.0
Requires-Dist: scikit-learn>=1.0.0
Requires-Dist: tqdm
Provides-Extra: uci
Requires-Dist: ucimlrepo>=0.0.7; extra == "uci"
Provides-Extra: dev
Requires-Dist: pytest>=7.0.0; extra == "dev"
Requires-Dist: pytest-cov>=4.0.0; extra == "dev"
Requires-Dist: black>=22.0.0; extra == "dev"
Requires-Dist: ruff>=0.1.0; extra == "dev"
Requires-Dist: mypy>=1.0.0; extra == "dev"
Provides-Extra: notebook
Requires-Dist: jupyter>=1.0.0; extra == "notebook"
Requires-Dist: matplotlib>=3.5.0; extra == "notebook"
Requires-Dist: seaborn>=0.11.0; extra == "notebook"
Provides-Extra: all
Requires-Dist: ucimlrepo>=0.0.7; extra == "all"
Requires-Dist: pytest>=7.0.0; extra == "all"
Requires-Dist: pytest-cov>=4.0.0; extra == "all"
Requires-Dist: black>=22.0.0; extra == "all"
Requires-Dist: ruff>=0.1.0; extra == "all"
Requires-Dist: mypy>=1.0.0; extra == "all"
Requires-Dist: jupyter>=1.0.0; extra == "all"
Requires-Dist: matplotlib>=3.5.0; extra == "all"
Requires-Dist: seaborn>=0.11.0; extra == "all"
Dynamic: license-file
